<?xml version="1.0" encoding="utf-8" ?><dwsync><file name="bulbs-50x50-fragments.png" server="www.novamara.com//var/www/html/" local="3483513258" remote="12073521462" /><file name="bg-strip-dark.png" server="www.novamara.com//var/www/html/" local="3483513257" remote="12073521754" /><file name="noise-pattern.png" server="www.novamara.com//var/www/html/" local="3483513260" remote="12073521754" /><file name="blank.png" server="www.novamara.com//var/www/html/" local="3483513257" remote="12073521760" /><file name="bulbs-32x32-bottom.png" server="www.novamara.com//var/www/html/" local="3483513257" remote="12073521761" /><file name="bulbs-32x32-left.png" server="www.novamara.com//var/www/html/" local="3483513257" remote="12073521762" /><file name="bulbs-32x32-right.png" server="www.novamara.com//var/www/html/" local="3483513257" remote="12073521762" /><file name="bulbs-32x32-top.png" server="www.novamara.com//var/www/html/" local="3483513257" remote="12073521763" /><file name="bulbs-50x50-bottom.png" server="www.novamara.com//var/www/html/" local="3483513258" remote="12073521765" /><file name="bulbs-50x50-left.png" server="www.novamara.com//var/www/html/" local="3483513258" remote="12073521766" /><file name="bulbs-50x50-right.png" server="www.novamara.com//var/www/html/" local="3483513258" remote="12073521767" /><file name="bulbs-50x50-top.png" server="www.novamara.com//var/www/html/" local="3483513258" remote="12073521768" /><file name="bulbs-50x50.png" server="www.novamara.com//var/www/html/" local="3483513258" remote="12073521769" /><file name="bulbs-64x64-bottom.png" server="www.novamara.com//var/www/html/" local="3483513258" remote="12073521770" /><file name="bulbs-64x64-left.png" server="www.novamara.com//var/www/html/" local="3483513258" remote="12073521771" /><file name="bulbs-64x64-right.png" server="www.novamara.com//var/www/html/" local="3483513259" remote="12073521772" /><file name="bulbs-64x64-top.png" server="www.novamara.com//var/www/html/" local="3483513259" remote="12073521773" /><file name="bulbs-72x72-bottom.png" server="www.novamara.com//var/www/html/" local="3483513259" remote="12073521774" /><file name="bulbs-72x72-left.png" server="www.novamara.com//var/www/html/" local="3483513259" remote="12073521775" /><file name="bulbs-72x72-right.png" server="www.novamara.com//var/www/html/" local="3483513259" remote="12073521777" /><file name="bulbs-72x72-top.png" server="www.novamara.com//var/www/html/" local="3483513259" remote="12073521777" /><file name="bulbs-96x96-bottom.png" server="www.novamara.com//var/www/html/" local="3483513259" remote="12073521779" /><file name="bulbs-96x96-left.png" server="www.novamara.com//var/www/html/" local="3483513260" remote="12073521780" /><file name="bulbs-96x96-right.png" server="www.novamara.com//var/www/html/" local="3483513260" remote="12073521781" /><file name="bulbs-96x96-top.png" server="www.novamara.com//var/www/html/" local="3483513260" remote="12073521782" /></dwsync>