<?xml version="1.0" encoding="utf-8" ?><dwsync><file name="justanotherhand-webfont.eot" server="www.novamara.com//var/www/html/" local="3434979656" remote="12027521524" /><file name="justanotherhand-webfont.ttf" server="www.novamara.com//var/www/html/" local="3434979656" remote="12027521526" /><file name="justanotherhand-webfont.woff" server="www.novamara.com//var/www/html/" local="3434979656" remote="12027521527" /><file name="JustAnotherHand_ttf_font_LICENSE.txt" server="www.novamara.com//var/www/html/" local="3434979656" remote="12027521528" /><file name="ostrich-rounded-webfont.eot" server="www.novamara.com//var/www/html/" local="3434979656" remote="12027521529" /><file name="ostrich-rounded-webfont.svg" server="www.novamara.com//var/www/html/" local="3434979656" remote="12027521530" /><file name="ostrich-rounded-webfont.ttf" server="www.novamara.com//var/www/html/" local="3434979656" remote="12027521531" /><file name="ostrich-rounded-webfont.woff" server="www.novamara.com//var/www/html/" local="3434979656" remote="12027521532" /></dwsync>